collabnet/__init__.py
collabnet/analysis.py
collabnet/data.py
collabnet/utils.py
collabnet-0.1.0.dist-info/WHEEL
collabnet-0.1.0.dist-info/METADATA
collabnet-0.1.0.dist-info/RECORD
