Metadata-Version: 2.3
Name: collabnet
Version: 0.1.0
Summary: Build collaboration networks from publication records.
Author: Malte Vogl
Author-email: Malte Vogl <vogl@gea.mpg.de>
Classifier: Programming Language :: Python :: 3
Classifier: License :: OSI Approved :: MIT License
Classifier: Operating System :: OS Independent
Requires-Dist: pyalex
Requires-Dist: pandas
Requires-Dist: igraph
Requires-Dist: tqdm
Requires-Dist: matplotlib
Requires-Dist: validator-collection>=1.5.0
Requires-Python: >=3.12
Project-URL: Bug Tracker, https://gitlab.gwdg.de/mpigea/dt/collabnet/-/issues
Project-URL: Homepage, https://gitlab.gwdg.de/mpigea/dt/collabnet
Project-URL: Project Homepage, https://modelsen.gea.mpg.de
